README.txt
setup.cfg
setup.py
Products/__init__.py
Products.CronUtility.egg-info/PKG-INFO
Products.CronUtility.egg-info/SOURCES.txt
Products.CronUtility.egg-info/dependency_links.txt
Products.CronUtility.egg-info/entry_points.txt
Products.CronUtility.egg-info/namespace_packages.txt
Products.CronUtility.egg-info/not-zip-safe
Products.CronUtility.egg-info/requires.txt
Products.CronUtility.egg-info/top_level.txt
Products/CronUtility/__init__.py
Products/CronUtility/configure.zcml
Products/CronUtility/interfaces.py
Products/CronUtility/utility.py
Products/CronUtility/browser/__init__.py
Products/CronUtility/browser/configure.zcml
Products/CronUtility/browser/view.py
docs/HISTORY.txt