Metadata-Version: 1.0
Name: Products.CronUtility
Version: 1.0
Summary: UNKNOWN
Home-page: http://raptus.com
Author: Raptus AG
Author-email: skaeser@raptus.com
License: GPL
Platform: UNKNOWN
Classifier: Programming Language :: Python
Classifier: Topic :: Software Development :: Libraries :: Python Modules
